minibanana/__init__.py
minibanana/core.py
minibanana-1.1.0.dist-info/METADATA
minibanana-1.1.0.dist-info/WHEEL
minibanana-1.1.0.dist-info/top_level.txt
minibanana-1.1.0.dist-info/RECORD
