Metadata-Version: 2.4
Name: minibanana
Version: 1.1.0
Summary: Un motor de videojuegos minimalista hecho con Tkinter, actualizaciones constantes
Home-page: https://github.com/banana-programadora/minibanana
Author: Bananaprogramadora
License: MIT
Requires-Python: >=3.8
Dynamic: author
Dynamic: home-page
Dynamic: license
Dynamic: requires-python
Dynamic: summary
